{
  "expense_reports": [
    {
      "id": 3026,
      "supporting_document_limit_date": null,
      "supporting_document_received_at": null,
      "paid_at": null,
      "status": "pending",
      "expenses": [
        {
          "id": 3032,
          "title": "Mlle Enzo Cousin",
          "at": "2016-11-12",
          "report_type": "digital",
          "amount": 0,
          "number_of_kilometers": 0,
          "toll_amount": 0,
          "total_amount": 0,
          "status": "pending",
          "reason": "",
          "starting_city": null,
          "arrival_city": null,
          "category": {
            "id": 3031,
            "name": "Benjamin Leclerc"
          },
          "transport": null,
          "documents": []
        }
      ],
      "user": {
        "id": 3025,
        "first_name": "Mathéo",
        "last_name": "Guillaume",
        "email": "bradly_jakubowski@bechtelarluettgen.org"
      }
    }
  ]
}